aladin/CanonicalDecorrelation.py
aladin/__init__.py
aladin/canonical_decorrelation.py
aladin-0.0.1.dist-info/METADATA
aladin-0.0.1.dist-info/WHEEL
aladin-0.0.1.dist-info/top_level.txt
aladin-0.0.1.dist-info/RECORD
